ScopusWp/__init__.py
ScopusWp/_wordpress.py
ScopusWp/config.ini
ScopusWp/config.py
ScopusWp/controller.py
ScopusWp/dat.py
ScopusWp/database.py
ScopusWp/extend.py
ScopusWp/ids.json
ScopusWp/install.py
ScopusWp/main.py
ScopusWp/register.py
ScopusWp/test.py
ScopusWp/util.py
ScopusWp/view.py
ScopusWp/scopus/__init__.py
ScopusWp/scopus/authors.ini
ScopusWp/scopus/config.py
ScopusWp/scopus/controller.py
ScopusWp/scopus/data.py
ScopusWp/scopus/database.py
ScopusWp/scopus/install.py
ScopusWp/scopus/observe.py
ScopusWp/scopus/persistency.py
ScopusWp/scopus/scopus.py
ScopusWp/scopus/templates/__init__.py
ScopusWp/scopus/templates/authors.ini
ScopusWp/scopus/templates/config.ini
ScopusWp/templates/__init__.py
ScopusWp/templates/config.ini
ScopusWp/wordpress/__init__.py
ScopusWp/wordpress/config.py
ScopusWp/wordpress/install.py
ScopusWp/wordpress/main.py
ScopusWp/wordpress/reference.py
ScopusWp/wordpress/views.py
ScopusWp/wordpress/wordpress.py
ScopusWp/wordpress/templates/button.html
ScopusWp/wordpress/templates/comment.html
ScopusWp/wordpress/templates/config.ini
ScopusWp/wordpress/templates/post.html
ScopusWp/wordpress/templates/post_excerpt.html
scopus.wp-0.3.0.83.dist-info/DESCRIPTION.rst
scopus.wp-0.3.0.83.dist-info/METADATA
scopus.wp-0.3.0.83.dist-info/RECORD
scopus.wp-0.3.0.83.dist-info/WHEEL
scopus.wp-0.3.0.83.dist-info/metadata.json
scopus.wp-0.3.0.83.dist-info/top_level.txt
