Metadata-Version: 2.0
Name: scopus.wp
Version: 0.3.0.83
Summary: A tool for a wordpress server which will automatically post science publications from scopus database
Home-page: https://github.com/the16thpythonist/ScopusWp
Author: Jonas Teufel
Author-email: jonseb1998@gmail.com
License: MIT
Platform: UNKNOWN
Requires-Python: >=3, <4
Requires-Dist: jinja2 (>=2.10)
Requires-Dist: jutily
Requires-Dist: memory-profiler
Requires-Dist: mysqlclient (>=1.2)
Requires-Dist: python-wordpress-xmlrpc (>=2.3)
Requires-Dist: requests (>=2.0)
Requires-Dist: sqlalchemy (>=1.2)
Requires-Dist: tabulate (>=0.8)
Requires-Dist: unidecode (>=0.4)
